[
{
  "Country": "Argentina",
  "Continent": "South America"
},
{
  "Country": "Australia",
  "Continent": "Oceania"
},
{
  "Country": "Brazil",
  "Continent": "South America"
},
{
  "Country": "Canada",
  "Continent": "North America"
},
{
  "Country": "China",
  "Continent": "Asia"
},
{
  "Country": "Germany",
  "Continent": "Europe"
},
{
  "Country": "France",
  "Continent": "Europe"
},
{
  "Country": "India",
  "Continent": "Asia"
},
{
  "Country": "Indonesia",
  "Continent": "Asia"
},
{
  "Country": "Italy",
  "Continent": "Europe"
},
{
  "Country": "Japan",
  "Continent": "Asia"
},
{
  "Country": "Mexico",
  "Continent": "America"
},
{
  "Country": "Russia",
  "Continent": "Asia"
},
{
  "Country": "Saudi Arabia",
  "Continent": "Asia"
},
{
  "Country": "South Africa",
  "Continent": "Africa"
},
{
  "Country": "Republic of Korea",
  "Continent": "Asia"
},
{
  "Country": "Turkey",
  "Continent": "Asia"
},
{
  "Country": "United Kingdom",
  "Continent": "Europe"
},
{
  "Country": "USA",
  "Continent": "North America"
}
]